overleaf_backup/__init__.py
overleaf_backup/backup.py
overleaf_backup/exceptions.py
overleaf_backup-1.0.0.dist-info/LICENSE
overleaf_backup-1.0.0.dist-info/METADATA
overleaf_backup-1.0.0.dist-info/WHEEL
overleaf_backup-1.0.0.dist-info/top_level.txt
overleaf_backup-1.0.0.dist-info/RECORD
